[
    {
        "designacao": "SemPontuacao",
        "morada": "dasdasda",
        "latitude": 313131,
        "longitude": 131231,
        "categoria_ponto": "Boa",
        "acessibilidade": "Bike",
        "classificacao": 0
    },
    {
        "designacao": "Dani",
        "morada": "1231",
        "latitude": 13132,
        "longitude": 1231,
        "categoria_ponto": "hyndia",
        "acessibilidade": "31",
        "classificacao": 0
    },
    {
        "designacao": "Casa do Mar",
        "morada": "Rua do Horizonte",
        "latitude": 31931,
        "longitude": 31231,
        "categoria_ponto": "Boa",
        "acessibilidade": "Bike",
        "classificacao": 0
    },
    {
        "designacao": "Joao",
        "morada": "Rua do 1",
        "latitude": 13131,
        "longitude": 3131,
        "categoria_ponto": "Boa",
        "acessibilidade": "Bike",
        "classificacao": 0
    },
    {
        "designacao": "EmBloco",
        "morada": "123131",
        "latitude": 1231,
        "longitude": 11,
        "categoria_ponto": "Ok",
        "acessibilidade": "Bike",
        "classificacao": 0
    }
]